json_autoarray/JSONAutoArray.py
json_autoarray/__init__.py
JSONAutoArray-1.0.4.dist-info/LICENSE.txt
JSONAutoArray-1.0.4.dist-info/METADATA
JSONAutoArray-1.0.4.dist-info/WHEEL
JSONAutoArray-1.0.4.dist-info/top_level.txt
JSONAutoArray-1.0.4.dist-info/RECORD
