Metadata-Version: 2.1
Name: JSONAutoArray
Version: 1.0.4
Summary: Write array to self-closing JSON file
Home-page: https://gitlab.com/doug.shawhan/json-autoarray
Author: Doug Shawhan
Author-email: doug.shawhan@gmail.com
Maintainer: Doug Shawhan
Maintainer-email: doug.shawhan@gmail.com
License: Copyright 2014 Doug Shawhan        
Download-URL: https://gitlab.com/doug.shawhan/json-autoarray
Project-URL: Bug Tracker, https://gitlab.com/doug.shawhan/jsonautoarray/
Project-URL: Source Code, https://gitlab.com/doug.shawhan/jsonautoarray/master
Project-URL: Development Version, https://gitlab.com/doug.shawhan/jsonautoarray/dev
Project-URL: Documentation, https://jsonautoarray.readthedocs.io
Keywords: ETL,Database
Platform: UNKNOWN
Classifier: Intended Audience :: Developers
Classifier: License :: OSI Approved :: BSD License
Classifier: Development Status :: 5 - Production/Stable
Classifier: Programming Language :: Python :: 3
